README
setup.py
src/django_hresume.egg-info/PKG-INFO
src/django_hresume.egg-info/SOURCES.txt
src/django_hresume.egg-info/dependency_links.txt
src/django_hresume.egg-info/requires.txt
src/django_hresume.egg-info/top_level.txt
src/hresume/__init__.py
src/hresume/admin.py
src/hresume/models.py
src/hresume/tests.py
src/hresume/testsettings.py
src/hresume/views.py