Metadata-Version: 1.0
Name: django-hresume
Version: 0.1
Summary: A resume application for django, presented using the hresume microformat
Home-page: http://github.com/wscoble/django-hresume
Author: Scott Scoble
Author-email: sscoble@scottfolio.us
License: LGPL
Platform: UNKNOWN
Classifier: Development Status :: 1 - Planning
Classifier: Framework :: Django
Classifier: Intended Audience :: Developers
Classifier: License :: OSI Approved :: GNU Library or Lesser General Public License (LGPL)
Classifier: Natural Language :: English
Classifier: Operating System :: OS Independent
Classifier: Programming Language :: Python
Classifier: Topic :: Internet :: WWW/HTTP
